astwro/__init__.py
astwro/version.py
astwro/config/__init__.py
astwro/config/config.py
astwro/config/logger.py
astwro/config/config/astwro.cfg
astwro/coord/CoordMatch.py
astwro/coord/Sky2XY.py
astwro/coord/WCSUtilsRunner.py
astwro/coord/XY2Sky.py
astwro/coord/__init__.py
astwro/coord/coord_tools.py
astwro/coord/plots.py
astwro/coord/tests/__init__.py
astwro/coord/tests/test_coordmatch.py
astwro/coord/tests/test_wcs_conv.py
astwro/exttools/Runner.py
astwro/exttools/__init__.py
astwro/exttools/output_processors.py
astwro/optim/Individual.py
astwro/optim/ScoreFunction.py
astwro/optim/__init__.py
astwro/phot/__init__.py
astwro/phot/dphot.py
astwro/phot/iphas.py
astwro/phot/lc_io.py
astwro/phot/phot_error.py
astwro/phot/plots.py
astwro/phot/stype.py
astwro/phot/tests/__init__.py
astwro/phot/tests/dphot_test.py
astwro/phot/tests/iphas_test.py
astwro/phot/tests/phot_err_test.py
astwro/phot/tests/stype_test.py
astwro/pydaophot/Allstar.py
astwro/pydaophot/DAORunner.py
astwro/pydaophot/Daophot.py
astwro/pydaophot/OutputProviders.py
astwro/pydaophot/__init__.py
astwro/pydaophot/_version.py
astwro/pydaophot/config/allstar.opt
astwro/pydaophot/config/daophot.opt
astwro/pydaophot/config/photo.opt
astwro/pydaophot/config/pydaophot.cfg
astwro/pydaophot/tests/__init__.py
astwro/pydaophot/tests/test_runners.py
astwro/sampledata/NGC6871.als
astwro/sampledata/NGC6871.ap
astwro/sampledata/NGC6871.coo
astwro/sampledata/NGC6871.fits
astwro/sampledata/NGC6871.lst
astwro/sampledata/NGC6871.nei
astwro/sampledata/NGC6871.psf
astwro/sampledata/__init__.py
astwro/sampledata/__init__.pyc
astwro/sampledata/astrometry.head
astwro/sampledata/daophot.opt
astwro/sampledata/i.err
astwro/sex/Scamp.py
astwro/sex/Sextractor.py
astwro/sex/__init__.py
astwro/sex/config/__init__.py
astwro/sex/tests/__init__.py
astwro/sex/tests/test_sex_sacamp.py
astwro/starlist/StarList.py
astwro/starlist/__init__.py
astwro/starlist/_version.py
astwro/starlist/daofiles.py
astwro/starlist/ds9.py
astwro-0.7.5.dist-info/LICENCE
astwro-0.7.5.dist-info/METADATA
astwro-0.7.5.dist-info/WHEEL
astwro-0.7.5.dist-info/entry_points.txt
astwro-0.7.5.dist-info/top_level.txt
astwro-0.7.5.dist-info/RECORD
