Metadata-Version: 2.1
Name: astwro
Version: 0.7.5
Summary: Astro tools
Home-page: https://github.com/majkelx/astwro
Author: Mikolaj Kaluszynski, Astronomical Institute of Wroclaw University
Author-email: UNKNOWN
License: MIT
Keywords: daophot photometry
Platform: UNKNOWN
Classifier: Development Status :: 3 - Alpha
Classifier: Intended Audience :: Science/Research
Classifier: Topic :: Scientific/Engineering :: Astronomy
Classifier: License :: OSI Approved :: MIT License
Classifier: Programming Language :: Python :: 3
Classifier: Programming Language :: Python :: 3.5
Classifier: Programming Language :: Python :: 2
Classifier: Programming Language :: Python :: 2.7
Requires-Dist: pandas
Requires-Dist: astropy
Requires-Dist: scipy
Requires-Dist: deap
Requires-Dist: bitarray (>=0.8munch)
